configaro.py
configaro-1.0.5.dist-info/LICENSE
configaro-1.0.5.dist-info/METADATA
configaro-1.0.5.dist-info/WHEEL
configaro-1.0.5.dist-info/top_level.txt
configaro-1.0.5.dist-info/zip-safe
configaro-1.0.5.dist-info/RECORD
