Metadata-Version: 2.1
Name: configaro
Version: 1.0.5
Summary: A Python 3.6 configuration library that's music to your ears.
Home-page: https://github.com/mojochao/configaro
Author: Allen Gooch
Author-email: allen.gooch@gmail.com
Maintainer: Allen Gooch
Maintainer-email: allen.gooch@gmail.com
License: MIT
Keywords: configuration,utility
Platform: UNKNOWN
Classifier: Development Status :: 5 - Production/Stable
Classifier: Natural Language :: English
Classifier: Programming Language :: Python :: 3.6
Classifier: License :: OSI Approved :: MIT License
Requires-Dist: munch
